apps/backend/__init__.py
apps/complex/__init__.py
apps/complex/sub/__init__.py
apps/frontend/__init__.py
docs/__init__.py
docs/conf.py
hosted_flasks/__init__.py
hosted_flasks/__main__.py
hosted_flasks/frontpage.py
hosted_flasks/loader.py
hosted_flasks/monkeypatch.py
hosted_flasks/server.py
hosted_flasks/statistics.py
hosted_flasks/utils.py
hosted_flasks/frontpage/index.html
hosted_flasks/frontpage/stats.html
hosted_flasks/frontpage/static/android-chrome-192x192.png
hosted_flasks/frontpage/static/android-chrome-512x512.png
hosted_flasks/frontpage/static/apple-touch-icon.png
hosted_flasks/frontpage/static/chart.js
hosted_flasks/frontpage/static/favicon-16x16.png
hosted_flasks/frontpage/static/favicon-32x32.png
hosted_flasks/frontpage/static/favicon.ico
hosted_flasks/frontpage/static/robots.txt
hosted_flasks/frontpage/static/site.webmanifest
hosted_flasks/frontpage/static/bootstrap-5.3.3-dist/css/bootstrap-grid.css
hosted_flasks/frontpage/static/bootstrap-5.3.3-dist/css/bootstrap-grid.css.map
hosted_flasks/frontpage/static/bootstrap-5.3.3-dist/css/bootstrap-grid.min.css
hosted_flasks/frontpage/static/bootstrap-5.3.3-dist/css/bootstrap-grid.min.css.map
hosted_flasks/frontpage/static/bootstrap-5.3.3-dist/css/bootstrap-grid.rtl.css
hosted_flasks/frontpage/static/bootstrap-5.3.3-dist/css/bootstrap-grid.rtl.css.map
hosted_flasks/frontpage/static/bootstrap-5.3.3-dist/css/bootstrap-grid.rtl.min.css
hosted_flasks/frontpage/static/bootstrap-5.3.3-dist/css/bootstrap-grid.rtl.min.css.map
hosted_flasks/frontpage/static/bootstrap-5.3.3-dist/css/bootstrap-reboot.css
hosted_flasks/frontpage/static/bootstrap-5.3.3-dist/css/bootstrap-reboot.css.map
hosted_flasks/frontpage/static/bootstrap-5.3.3-dist/css/bootstrap-reboot.min.css
hosted_flasks/frontpage/static/bootstrap-5.3.3-dist/css/bootstrap-reboot.min.css.map
hosted_flasks/frontpage/static/bootstrap-5.3.3-dist/css/bootstrap-reboot.rtl.css
hosted_flasks/frontpage/static/bootstrap-5.3.3-dist/css/bootstrap-reboot.rtl.css.map
hosted_flasks-0.6.1.dist-info/licenses/LICENSE.txt
hosted_flasks-0.6.1.dist-info/METADATA
hosted_flasks-0.6.1.dist-info/WHEEL
hosted_flasks-0.6.1.dist-info/entry_points.txt
hosted_flasks-0.6.1.dist-info/top_level.txt
hosted_flasks-0.6.1.dist-info/RECORD
