Metadata-Version: 2.4
Name: hosted-flasks
Version: 0.6.1
Summary: serve flask apps side by side
Home-page: https://github.com/christophevg/hosted-flasks
Author: Christophe VG
License: MIT
Keywords: multiple flask apps
Classifier: Programming Language :: Python :: 3.8
Classifier: Programming Language :: Python :: 3.9
Classifier: Programming Language :: Python :: 3.10
Classifier: Programming Language :: Python :: 3.11
Classifier: Environment :: Web Environment
Classifier: Intended Audience :: Developers
License-File: LICENSE.txt
Requires-Dist: Flask
Requires-Dist: python-dotenv
Requires-Dist: eventlet
Requires-Dist: pyyaml
Requires-Dist: humanize
Requires-Dist: markdown
Requires-Dist: ua-parser
Dynamic: author
Dynamic: classifier
Dynamic: description
Dynamic: description-content-type
Dynamic: home-page
Dynamic: keywords
Dynamic: license
Dynamic: license-file
Dynamic: requires-dist
Dynamic: summary
